__init__.py
aidenlib/main.py
aidenlib/cogs/helper_cog.py
AidenLib-0.1.4.dist-info/LICENSE
AidenLib-0.1.4.dist-info/METADATA
AidenLib-0.1.4.dist-info/WHEEL
AidenLib-0.1.4.dist-info/top_level.txt
AidenLib-0.1.4.dist-info/RECORD
